{
    "sobre_mim": "Sou uma pessoa intrinsecamente motivada e disciplinada, características que me impulsionam a enfrentar desafios com determinação e a manter sempre um elevado nível de produtividade em todas as atividades em que me envolvo. O meu percurso profissional levou-me a trabalhar e estudar em diversos locais, reforçando a minha convicção de que com foco, ambição e motivação, não há obstáculos inultrapassáveis. Uma das minhas maiores competências é a minha capacidade de comunicação. Esta permite-me interagir de uma forma eficaz com os colegas e com os clientes, o que me permite garantir um excelente atendimento. Sou uma pessoa proativa, responsável e enérgica e acredito seguramente que a manutenção de um ambiente de trabalho positivo é fundamental para o sucesso da equipa e a satisfação dos clientes. Além disso o meu compromisso com um estilo de vida saudável, incluindo a prática regular de desporto e uma alimentação equilibrada contribui para o meu bem-estar e vitalidade. O meu profundo interesse na área da Conservação e Restauro, com um foco especial em vidro e metais, motiva-me constantemente a aprofundar o meu conhecimento e habilidades.",
    "email": "inessambado@gmail.com",
    "linkedin": "https://www.linkedin.com/in/in%C3%AAs-sambado-840171ba/",
    "nome": "Inês Sambado ",
    "titulo": "Conservadora-Restauradora",
    "especialidades": "Fotografia",
    "formacao": "Licenciatura em Conservação e Restauro",
    "instagram": "https://www.instagram.com/inessambado/",
    "cv_path": "cv_ines_sambado.pdf",
    "password": "Restauro2026!"
}